repo2data/__init__.py
repo2data/repo2data.py
repo2data/utils.py
repo2data-2.9.7.dist-info/LICENSE
repo2data-2.9.7.dist-info/METADATA
repo2data-2.9.7.dist-info/WHEEL
repo2data-2.9.7.dist-info/entry_points.txt
repo2data-2.9.7.dist-info/top_level.txt
repo2data-2.9.7.dist-info/RECORD
