Metadata-Version: 2.1
Name: repo2data
Version: 2.9.7
Summary: A Python package to automate the fetching and extraction of data from remote sources like Amazon S3, Zeonodo, Datalad, Google Drive, OSF, or any public download URL.
Author-email: ltetrel <roboneurolibre@gmail.com>, agahkarakuzu <agahkarakuzu@gmail.com>
License: MIT License
Project-URL: Homepage, https://github.com/SIMEXP/Repo2Data
Keywords: neurolibre,open-data,reproducible,osf,zenodo,datalad,conp,gdown,aws
Classifier: Programming Language :: Python :: 3
Classifier: License :: OSI Approved :: MIT License
Classifier: Operating System :: OS Independent
Requires-Python: >=3.7
License-File: LICENSE
Requires-Dist: awscli
Requires-Dist: patool
Requires-Dist: datalad
Requires-Dist: requests
Requires-Dist: osfclient
Requires-Dist: gdown
Requires-Dist: zenodo-get
Requires-Dist: requests
